{
  "dashboardTitle": "FIFA World Cup 2026 - Global Security Desk",
  "overview": {
    "status": "Operational",
    "hostCities": 16
  },
  "metrics": {
    "p1": 0,
    "p2": 0,
    "p3": 18
  },
  "watchlist": [
    {
      "team": "Argentina",
      "location": "Miami",
      "note": "High fan concentration"
    },
    {
      "team": "Brazil",
      "location": "Orlando",
      "note": "Traffic congestion expected"
    },
    {
      "team": "USA",
      "location": "Atlanta",
      "note": "Enhanced perimeter security"
    },
    {
      "team": "France",
      "location": "Dallas",
      "note": "Heavy media presence"
    }
  ],
  "hostCities": [
    {
      "region": "Western",
      "name": "Los Angeles",
      "stadium": "SoFi Stadium",
      "risk": "high"
    },
    {
      "region": "Western",
      "name": "San Francisco Bay Area",
      "stadium": "Levi's Stadium",
      "risk": "medium"
    },
    {
      "region": "Western",
      "name": "Seattle",
      "stadium": "Lumen Field",
      "risk": "low"
    },
    {
      "region": "Western",
      "name": "Vancouver",
      "stadium": "BC Place",
      "risk": "low"
    },
    {
      "region": "Western",
      "name": "Guadalajara",
      "stadium": "Estadio Akron",
      "risk": "low"
    },
    {
      "region": "Central",
      "name": "Mexico City",
      "stadium": "Estadio Azteca",
      "risk": "high"
    },
    {
      "region": "Central",
      "name": "Houston",
      "stadium": "NRG Stadium",
      "risk": "medium"
    },
    {
      "region": "Central",
      "name": "Dallas",
      "stadium": "AT&T Stadium",
      "risk": "medium"
    },
    {
      "region": "Central",
      "name": "Kansas City",
      "stadium": "Arrowhead Stadium",
      "risk": "medium"
    },
    {
      "region": "Central",
      "name": "Monterrey",
      "stadium": "Estadio BBVA",
      "risk": "low"
    },
    {
      "region": "Eastern",
      "name": "New York / New Jersey",
      "stadium": "MetLife Stadium",
      "risk": "medium"
    },
    {
      "region": "Eastern",
      "name": "Toronto",
      "stadium": "BMO Field",
      "risk": "medium"
    },
    {
      "region": "Eastern",
      "name": "Atlanta",
      "stadium": "Mercedes-Benz Stadium",
      "risk": "medium"
    },
    {
      "region": "Eastern",
      "name": "Miami",
      "stadium": "Hard Rock Stadium",
      "risk": "medium"
    },
    {
      "region": "Eastern",
      "name": "Boston",
      "stadium": "Gillette Stadium",
      "risk": "low"
    },
    {
      "region": "Eastern",
      "name": "Philadelphia",
      "stadium": "Lincoln Financial Field",
      "risk": "low"
    }
  ],
  "risks": [
    {
      "title": "How much are cheapest tickets for Spain vs. Argentina World Cup Final in NJ?",
      "risk": "low",
      "severityText": "P3 ADVISORY",
      "status": "VERIFIED",
      "description": "The elite clubs will meet at MetLife Stadium on Sunday, July 19.",
      "timestamp": "2026-07-17T16:05:04.507917Z",
      "links": [
        {
          "label": "Source",
          "url": "https://nypost.com/2026/07/16/ticket-sales/how-much-are-cheapest-tickets-for-spain-argentina-world-cup-final/"
        }
      ]
    },
    {
      "title": "Barcelona building new state-of-the-art gym at Ciutat Esportiva ahead of new season",
      "risk": "low",
      "severityText": "P3 ADVISORY",
      "status": "VERIFIED",
      "description": "As the 2026 FIFA World Cup reach its final stage, Barcelona have already started preparing for the season ahead.Much of the focus is on work surrounding the Camp Nou, with the club notably looking to ...",
      "timestamp": "2026-07-17T16:05:04.508014Z",
      "links": [
        {
          "label": "Source",
          "url": "https://barcauniversal.com/barcelona-building-new-state-of-the-art-gym-at-ciutat-esportiva-ahead-of-new-season/"
        }
      ]
    },
    {
      "title": "2026 World Cup: Messi overtakes Mbappe in top scorer race",
      "risk": "low",
      "severityText": "P3 ADVISORY",
      "status": "VERIFIED",
      "description": "Argentina captain Lionel Messi has moved ahead of France forward Kylian Mbappe in the race for the 2026 FIFA World Cup Golden Boot after helping his side book a place in the final.\nThe post 2026 World Cup: Messi overtakes Mbappe in top scorer race appeared fi\u2026",
      "timestamp": "2026-07-17T16:05:04.508226Z",
      "links": [
        {
          "label": "Source",
          "url": "https://www.vanguardngr.com/2026/07/2026-world-cup-messi-overtakes-mbappe-in-top-scorer-race/"
        }
      ]
    },
    {
      "title": "Spain World Cup Final Preview: Journey, Team News, Predicted Lineup",
      "risk": "low",
      "severityText": "P3 ADVISORY",
      "status": "VERIFIED",
      "description": "Spain faces Argentina in the 2026 World Cup final at MetLife Stadium on July 19, with La Roja based in Montclair, NJ and a full squad available for Sunday's clash.",
      "timestamp": "2026-07-17T16:05:04.508325Z",
      "links": [
        {
          "label": "Source",
          "url": "https://www.forbes.com/sites/samleveridge/2026/07/16/spain-world-cup-final-preview-journey-team-news-predicted-lineup/"
        }
      ]
    },
    {
      "title": "Lionel Messi's heroics, Cape Verde's run, viral ducks and other top moments from the 2026 World Cup",
      "risk": "low",
      "severityText": "P3 ADVISORY",
      "status": "VERIFIED",
      "description": "The past month has been filled with a number of lasting images and memories on and off the field.",
      "timestamp": "2026-07-17T16:05:04.508346Z",
      "links": [
        {
          "label": "Source",
          "url": "https://sports.yahoo.com/soccer/article/lionel-messis-heroics-cape-verdes-run-viral-ducks-and-other-top-moments-from-the-2026-world-cup-143512363.html"
        }
      ]
    },
    {
      "title": "Ticket prices for England vs France at Miami Stadium have crashed since semi-final results",
      "risk": "low",
      "severityText": "P3 ADVISORY",
      "status": "VERIFIED",
      "description": "There are two more games of the 2026 World Cup to play out in the United States, but fans really don\u2019t seem to care about one. After beating England 2-1 in the semi-final on Wednesday, Argentina will play France in the final at the New York New Jersey Stadium\u2026",
      "timestamp": "2026-07-17T16:05:04.508425Z",
      "links": [
        {
          "label": "Source",
          "url": "https://www.hitc.com/ticket-prices-for-england-vs-france-at-miami-stadium-have-crashed-since-semi-final-results/"
        }
      ]
    },
    {
      "title": "2026 FIFA World Cup Final: How to Find Last-Minute Tickets",
      "risk": "low",
      "severityText": "P3 ADVISORY",
      "status": "VERIFIED",
      "description": "Spain will play defending champions Argentina on July 19th at New York/New Jersey Stadium.\n2026 FIFA World Cup Final: How to Find Last-Minute Tickets\nPaolo Ragusa",
      "timestamp": "2026-07-17T16:05:04.508465Z",
      "links": [
        {
          "label": "Source",
          "url": "https://consequence.net/2026/07/2026-fifa-world-cup-final-last-minute-tickets/"
        }
      ]
    },
    {
      "title": "The 2026 FIFA World Cup announcer rankings",
      "risk": "low",
      "severityText": "P3 ADVISORY",
      "status": "VERIFIED",
      "description": "Last month, we asked you, the readers, to grade the nine Fox Sports broadcast teams calling games at the 2026 FIFA World Cup. Voters were asked to assign letter grades ranging from A through F to as many or as few teams as they\u2019d like. Now, we\u2019ve tabulated al\u2026",
      "timestamp": "2026-07-17T16:05:04.508651Z",
      "links": [
        {
          "label": "Source",
          "url": "https://awfulannouncing.com/soccer/the-2026-fifa-world-cup-announcer-rankings.html"
        }
      ]
    },
    {
      "title": "2026 World Cup Final Ticket Prices to Shatter Record for Sports Event on American Soil",
      "risk": "low",
      "severityText": "P3 ADVISORY",
      "status": "VERIFIED",
      "description": "Tickets for the 2026 World Cup final aren\u2019t just expensive. They are set to be the most costly ever for [\u2026]",
      "timestamp": "2026-07-17T16:05:04.508677Z",
      "links": [
        {
          "label": "Source",
          "url": "https://sportsnaut.com/soccer/2026-world-cup-final-ticket-prices-break-records"
        }
      ]
    },
    {
      "title": "NJ Governor Slams FIFA\u2019s \u2018Money Grab\u2019 Over Sales of MetLife World Cup Pitch",
      "risk": "low",
      "severityText": "P3 ADVISORY",
      "status": "VERIFIED",
      "description": "New Jersey Governor Mikie Sherrill's office has criticized FIFA's decision to sell pieces of the 2026 World Cup final pitch from MetLife Stadium, arguing that taxpayers should share in any proceeds because the state paid most of the cost of installing the fie\u2026",
      "timestamp": "2026-07-17T16:05:04.508705Z",
      "links": [
        {
          "label": "Source",
          "url": "https://biztoc.com/x/337154dc32181753"
        }
      ]
    },
    {
      "title": "How to Watch the 2026 FIFA World Cup Final Live Without Cable (Even for Free)",
      "risk": "low",
      "severityText": "P3 ADVISORY",
      "status": "VERIFIED",
      "description": "This weekend, the World Cup will wrap up with France vs. England in the bronze final and Spain vs. Argentina in the big finale. Which team will be crowned the ultimate champion? Here's how to tune in live.\nThe World Cup is wrapping up. Following Spain's impre\u2026",
      "timestamp": "2026-07-17T16:05:04.508769Z",
      "links": [
        {
          "label": "Source",
          "url": "https://uk.pcmag.com/video-streaming-services/161984/how-to-watch-2026-fifa-world-cup-final-live-stream-for-free"
        }
      ]
    },
    {
      "title": "All 11 last-minute winners at the World Cup",
      "risk": "low",
      "severityText": "P3 ADVISORY",
      "status": "VERIFIED",
      "description": "Watch all 11 winning goals scored in stoppage time at the 2026 Fifa World Cup.",
      "timestamp": "2026-07-17T16:05:04.508814Z",
      "links": [
        {
          "label": "Source",
          "url": "https://www.bbc.co.uk/sport/football/videos/cp8xn9y46xdo"
        }
      ]
    },
    {
      "title": "19-year-old Messi-Yamal photo resurfaces ahead of world cup final",
      "risk": "low",
      "severityText": "P3 ADVISORY",
      "status": "VERIFIED",
      "description": "A 19-year-old photo of Lionel Messi bathing baby Lamine Yamal has resurfaced ahead of the 2026 World Cup final. Discover this extraordinary Messi Yamal pho\n\nRead More: https://punchng.com/19-year-old-messi-yamal-photo-resurfaces-ahead-of-world-cup-final/",
      "timestamp": "2026-07-17T16:05:04.508853Z",
      "links": [
        {
          "label": "Source",
          "url": "https://punchng.com/19-year-old-messi-yamal-photo-resurfaces-ahead-of-world-cup-final/"
        }
      ]
    },
    {
      "title": "Messi Shines, FOX Sports is Golden with Record-Breaking England-Argentina FIFA World Cup 2026 Semifinal",
      "risk": "low",
      "severityText": "P3 ADVISORY",
      "status": "VERIFIED",
      "description": "15.063 million viewers watched Lionel Messi and Argentina knock out England in the semifinal Wednesday afternoon on FOX.",
      "timestamp": "2026-07-17T16:05:04.508993Z",
      "links": [
        {
          "label": "Source",
          "url": "http://www.thefutoncritic.com/ratings/2026/07/16/messi-shines-fox-sports-is-golden-with-record-breaking-england-argentina-fifa-world-cup-2026-semifinal-271511/20260716fox01/"
        }
      ]
    },
    {
      "title": "The 2026 World Cup has been a tournament where alcohol brands hoped to win influence through sponsorship",
      "risk": "low",
      "severityText": "P3 ADVISORY",
      "status": "VERIFIED",
      "description": "Tournament sponsors have a captive audience.",
      "timestamp": "2026-07-17T16:05:04.509062Z",
      "links": [
        {
          "label": "Source",
          "url": "https://theconversation.com/the-2026-world-cup-has-been-a-tournament-where-alcohol-brands-hoped-to-win-influence-through-sponsorship-287532"
        }
      ]
    },
    {
      "title": "England coach Thomas Tuchel eyes future after 2026 World Cup semifinal exit",
      "risk": "low",
      "severityText": "P3 ADVISORY",
      "status": "VERIFIED",
      "description": "Thomas Tuchel said he \"looks forward\" to his future as manager of England's national team after the Three Lions' brutal exit from the 2026 World Cup.",
      "timestamp": "2026-07-17T16:05:04.509135Z",
      "links": [
        {
          "label": "Source",
          "url": "https://www.upi.com/Sports_News/Soccer/2026/07/16/latam-world-cup-Thomas-Tuchel-England-future/9161784201874/"
        }
      ]
    },
    {
      "title": "DD.NYC Earns 2026 Webby Award Nomination for FIFA World Cup 26 New York New Jersey Website",
      "risk": "low",
      "severityText": "P3 ADVISORY",
      "status": "VERIFIED",
      "description": "The nomination recognizes the agency's work on a high-profile platform built for fans, media, and partners worldwide NEW YORK, July 16, 2026 /PRNewswire/ -- DD.NYC, a leading creative design agency, has announced that its official FIFA World Cup 26\u2122 New York \u2026",
      "timestamp": "2026-07-17T16:05:04.509289Z",
      "links": [
        {
          "label": "Source",
          "url": "https://www.prnewswire.com/news-releases/ddnyc-earns-2026-webby-award-nomination-for-fifa-world-cup-26-new-york-new-jersey-website-302827483.html"
        }
      ]
    },
    {
      "title": "FIFA World Cup 2026: Biggest takeaways from the semifinals",
      "risk": "low",
      "severityText": "P3 ADVISORY",
      "status": "VERIFIED",
      "description": "The semifinals are now behind us, with plenty of key moments and incidents to digest ahead of Sunday\u2019s final.",
      "timestamp": "2026-07-17T16:05:04.509376Z",
      "links": [
        {
          "label": "Source",
          "url": "https://www.aljazeera.com/sports/2026/7/16/fifa-world-cup-2026-biggest-takeaways-from-the-semifinals"
        }
      ]
    }
  ],
  "timeline": [
    {
      "date": "Jul 17",
      "loc": "New York / New Jersey",
      "event": "How much are cheapest tickets for Spain vs. Argentina World Cup Final in NJ?",
      "type": "News",
      "confidence": "Confirmed",
      "risk": "low",
      "impact": "P3 ADVISORY",
      "links": [
        {
          "label": "Source",
          "url": "https://nypost.com/2026/07/16/ticket-sales/how-much-are-cheapest-tickets-for-spain-argentina-world-cup-final/"
        }
      ]
    },
    {
      "date": "Jul 17",
      "loc": "Global",
      "event": "Barcelona building new state-of-the-art gym at Ciutat Esportiva ahead of new season",
      "type": "News",
      "confidence": "Confirmed",
      "risk": "low",
      "impact": "P3 ADVISORY",
      "links": [
        {
          "label": "Source",
          "url": "https://barcauniversal.com/barcelona-building-new-state-of-the-art-gym-at-ciutat-esportiva-ahead-of-new-season/"
        }
      ]
    },
    {
      "date": "Jul 17",
      "loc": "Global",
      "event": "2026 World Cup: Messi overtakes Mbappe in top scorer race",
      "type": "News",
      "confidence": "Confirmed",
      "risk": "low",
      "impact": "P3 ADVISORY",
      "links": [
        {
          "label": "Source",
          "url": "https://www.vanguardngr.com/2026/07/2026-world-cup-messi-overtakes-mbappe-in-top-scorer-race/"
        }
      ]
    },
    {
      "date": "Jul 17",
      "loc": "New York / New Jersey",
      "event": "Spain World Cup Final Preview: Journey, Team News, Predicted Lineup",
      "type": "News",
      "confidence": "Confirmed",
      "risk": "low",
      "impact": "P3 ADVISORY",
      "links": [
        {
          "label": "Source",
          "url": "https://www.forbes.com/sites/samleveridge/2026/07/16/spain-world-cup-final-preview-journey-team-news-predicted-lineup/"
        }
      ]
    },
    {
      "date": "Jul 17",
      "loc": "Global",
      "event": "Lionel Messi's heroics, Cape Verde's run, viral ducks and other top moments from the 2026 World Cup",
      "type": "News",
      "confidence": "Confirmed",
      "risk": "low",
      "impact": "P3 ADVISORY",
      "links": [
        {
          "label": "Source",
          "url": "https://sports.yahoo.com/soccer/article/lionel-messis-heroics-cape-verdes-run-viral-ducks-and-other-top-moments-from-the-2026-world-cup-143512363.html"
        }
      ]
    },
    {
      "date": "Jul 17",
      "loc": "Global",
      "event": "Ticket prices for England vs France at Miami Stadium have crashed since semi-final results",
      "type": "News",
      "confidence": "Confirmed",
      "risk": "low",
      "impact": "P3 ADVISORY",
      "links": [
        {
          "label": "Source",
          "url": "https://www.hitc.com/ticket-prices-for-england-vs-france-at-miami-stadium-have-crashed-since-semi-final-results/"
        }
      ]
    },
    {
      "date": "Jul 17",
      "loc": "Global",
      "event": "2026 FIFA World Cup Final: How to Find Last-Minute Tickets",
      "type": "News",
      "confidence": "Confirmed",
      "risk": "low",
      "impact": "P3 ADVISORY",
      "links": [
        {
          "label": "Source",
          "url": "https://consequence.net/2026/07/2026-fifa-world-cup-final-last-minute-tickets/"
        }
      ]
    },
    {
      "date": "Jul 17",
      "loc": "Global",
      "event": "The 2026 FIFA World Cup announcer rankings",
      "type": "News",
      "confidence": "Confirmed",
      "risk": "low",
      "impact": "P3 ADVISORY",
      "links": [
        {
          "label": "Source",
          "url": "https://awfulannouncing.com/soccer/the-2026-fifa-world-cup-announcer-rankings.html"
        }
      ]
    },
    {
      "date": "Jul 17",
      "loc": "Global",
      "event": "2026 World Cup Final Ticket Prices to Shatter Record for Sports Event on American Soil",
      "type": "News",
      "confidence": "Confirmed",
      "risk": "low",
      "impact": "P3 ADVISORY",
      "links": [
        {
          "label": "Source",
          "url": "https://sportsnaut.com/soccer/2026-world-cup-final-ticket-prices-break-records"
        }
      ]
    },
    {
      "date": "Jul 17",
      "loc": "New York / New Jersey",
      "event": "NJ Governor Slams FIFA\u2019s \u2018Money Grab\u2019 Over Sales of MetLife World Cup Pitch",
      "type": "News",
      "confidence": "Confirmed",
      "risk": "low",
      "impact": "P3 ADVISORY",
      "links": [
        {
          "label": "Source",
          "url": "https://biztoc.com/x/337154dc32181753"
        }
      ]
    },
    {
      "date": "Jul 17",
      "loc": "Global",
      "event": "How to Watch the 2026 FIFA World Cup Final Live Without Cable (Even for Free)",
      "type": "News",
      "confidence": "Confirmed",
      "risk": "low",
      "impact": "P3 ADVISORY",
      "links": [
        {
          "label": "Source",
          "url": "https://uk.pcmag.com/video-streaming-services/161984/how-to-watch-2026-fifa-world-cup-final-live-stream-for-free"
        }
      ]
    },
    {
      "date": "Jul 17",
      "loc": "Global",
      "event": "All 11 last-minute winners at the World Cup",
      "type": "News",
      "confidence": "Confirmed",
      "risk": "low",
      "impact": "P3 ADVISORY",
      "links": [
        {
          "label": "Source",
          "url": "https://www.bbc.co.uk/sport/football/videos/cp8xn9y46xdo"
        }
      ]
    },
    {
      "date": "Jul 17",
      "loc": "Global",
      "event": "19-year-old Messi-Yamal photo resurfaces ahead of world cup final",
      "type": "News",
      "confidence": "Confirmed",
      "risk": "low",
      "impact": "P3 ADVISORY",
      "links": [
        {
          "label": "Source",
          "url": "https://punchng.com/19-year-old-messi-yamal-photo-resurfaces-ahead-of-world-cup-final/"
        }
      ]
    },
    {
      "date": "Jul 17",
      "loc": "Global",
      "event": "Messi Shines, FOX Sports is Golden with Record-Breaking England-Argentina FIFA World Cup 2026 Semifinal",
      "type": "News",
      "confidence": "Confirmed",
      "risk": "low",
      "impact": "P3 ADVISORY",
      "links": [
        {
          "label": "Source",
          "url": "http://www.thefutoncritic.com/ratings/2026/07/16/messi-shines-fox-sports-is-golden-with-record-breaking-england-argentina-fifa-world-cup-2026-semifinal-271511/20260716fox01/"
        }
      ]
    },
    {
      "date": "Jul 17",
      "loc": "Global",
      "event": "The 2026 World Cup has been a tournament where alcohol brands hoped to win influence through sponsorship",
      "type": "News",
      "confidence": "Confirmed",
      "risk": "low",
      "impact": "P3 ADVISORY",
      "links": [
        {
          "label": "Source",
          "url": "https://theconversation.com/the-2026-world-cup-has-been-a-tournament-where-alcohol-brands-hoped-to-win-influence-through-sponsorship-287532"
        }
      ]
    },
    {
      "date": "Jul 17",
      "loc": "Global",
      "event": "England coach Thomas Tuchel eyes future after 2026 World Cup semifinal exit",
      "type": "News",
      "confidence": "Confirmed",
      "risk": "low",
      "impact": "P3 ADVISORY",
      "links": [
        {
          "label": "Source",
          "url": "https://www.upi.com/Sports_News/Soccer/2026/07/16/latam-world-cup-Thomas-Tuchel-England-future/9161784201874/"
        }
      ]
    },
    {
      "date": "Jul 17",
      "loc": "Global",
      "event": "DD.NYC Earns 2026 Webby Award Nomination for FIFA World Cup 26 New York New Jersey Website",
      "type": "News",
      "confidence": "Confirmed",
      "risk": "low",
      "impact": "P3 ADVISORY",
      "links": [
        {
          "label": "Source",
          "url": "https://www.prnewswire.com/news-releases/ddnyc-earns-2026-webby-award-nomination-for-fifa-world-cup-26-new-york-new-jersey-website-302827483.html"
        }
      ]
    },
    {
      "date": "Jul 17",
      "loc": "Global",
      "event": "FIFA World Cup 2026: Biggest takeaways from the semifinals",
      "type": "News",
      "confidence": "Confirmed",
      "risk": "low",
      "impact": "P3 ADVISORY",
      "links": [
        {
          "label": "Source",
          "url": "https://www.aljazeera.com/sports/2026/7/16/fifa-world-cup-2026-biggest-takeaways-from-the-semifinals"
        }
      ]
    }
  ],
  "lastUpdated": "2026-07-17T16:05:04.509496Z"
}